LICENSE
MANIFEST.in
README.md
pyproject.toml
requirements-dev.txt
requirements-docs.txt
requirements-optional.txt
requirements-test.txt
requirements.txt
setup.cfg
setup.py
docs/.buildinfo
docs/.nojekyll
docs/genindex.html
docs/index.html
docs/objects.inv
docs/py-modindex.html
docs/search.html
docs/searchindex.js
docs/_images/tutorial_algorithm_explained_14_0.png
docs/_images/tutorial_algorithm_explained_15_0.png
docs/_images/tutorial_algorithm_explained_16_0.png
docs/_images/tutorial_algorithm_explained_17_0.png
docs/_images/tutorial_algorithm_explained_18_0.png
docs/_images/tutorial_algorithm_explained_19_0.png
docs/_images/tutorial_algorithm_explained_20_0.png
docs/_images/tutorial_algorithm_explained_21_0.png
docs/_images/tutorial_algorithm_explained_25_0.png
docs/_images/tutorial_algorithm_explained_26_0.png
docs/_images/tutorial_algorithm_explained_29_1.png
docs/_images/tutorial_algorithm_explained_31_1.png
docs/_images/tutorial_algorithm_explained_35_0.png
docs/_images/tutorial_algorithm_explained_38_0.png
docs/_images/tutorial_algorithm_explained_39_0.png
docs/_images/tutorial_algorithm_explained_40_0.png
docs/_images/tutorial_algorithm_explained_42_0.png
docs/_images/tutorial_algorithm_explained_43_0.png
docs/_images/tutorial_algorithm_explained_44_1.png
docs/_images/tutorial_algorithm_explained_46_1.png
docs/_images/tutorial_algorithm_explained_48_0.png
docs/_images/tutorial_algorithm_explained_50_0.png
docs/_images/tutorial_basic_usage_29_0.png
docs/_images/tutorial_basic_usage_30_0.png
docs/_images/tutorial_basic_usage_30_01.png
docs/_images/tutorial_hierarchical_clustering_basics_14_0.png
docs/_images/tutorial_hierarchical_clustering_basics_16_0.png
docs/_images/tutorial_hierarchical_clustering_basics_18_1.png
docs/_images/tutorial_hierarchical_clustering_basics_20_0.png
docs/_images/tutorial_hierarchical_clustering_basics_20_1.png
docs/_images/tutorial_hierarchical_clustering_basics_23_0.png
docs/_images/tutorial_hierarchical_clustering_basics_29_0.png
src/cnnclustering.egg-info/PKG-INFO
src/cnnclustering.egg-info/SOURCES.txt
src/cnnclustering.egg-info/dependency_links.txt
src/cnnclustering.egg-info/not-zip-safe
src/cnnclustering.egg-info/requires.txt
src/cnnclustering.egg-info/top_level.txt