Metadata-Version: 2.1
Name: cnnclustering
Version: 0.5.0
Summary: A Python package for common-nearest-neighbours clustering
Home-page: https://github.com/janjoswig/CommonNNClustering
Author: Jan-Oliver Joswig
Author-email: jan.joswig@fu-berlin.de
License: UNKNOWN
Keywords: Density-based clustering
Platform: UNKNOWN
Classifier: Development Status :: 3 - Alpha
Classifier: Programming Language :: Python :: 3
Classifier: Programming Language :: Python :: 3.6
Classifier: Programming Language :: Python :: 3.7
Classifier: Programming Language :: Python :: 3.8
Classifier: Programming Language :: Python :: 3.9
Classifier: License :: OSI Approved :: MIT License
Classifier: Operating System :: OS Independent
Provides-Extra: optional
Provides-Extra: dev
Provides-Extra: docs
Provides-Extra: test
License-File: LICENSE
